{
  "left_etf_id": "US-SMH",
  "right_etf_id": "US-SOXQ",
  "overlap_ratio": 0.506562,
  "shared_holdings_count": 9,
  "shared_holdings": [
    {
      "holding_symbol": "NVDA",
      "left_weight": 0.177539,
      "right_weight": 0.103337,
      "overlap_weight": 0.103337
    },
    {
      "holding_symbol": "MU",
      "left_weight": 0.058447,
      "right_weight": 0.086417,
      "overlap_weight": 0.058447
    },
    {
      "holding_symbol": "AMAT",
      "left_weight": 0.057252,
      "right_weight": 0.058391,
      "overlap_weight": 0.057252
    },
    {
      "holding_symbol": "AVGO",
      "left_weight": 0.054053,
      "right_weight": 0.076832,
      "overlap_weight": 0.054053
    },
    {
      "holding_symbol": "KLAC",
      "left_weight": 0.053398,
      "right_weight": 0.057067,
      "overlap_weight": 0.053398
    },
    {
      "holding_symbol": "LRCX",
      "left_weight": 0.052307,
      "right_weight": 0.049503,
      "overlap_weight": 0.049503
    },
    {
      "holding_symbol": "ASML",
      "left_weight": 0.049543,
      "right_weight": 0.044833,
      "overlap_weight": 0.044833
    },
    {
      "holding_symbol": "INTC",
      "left_weight": 0.050409,
      "right_weight": 0.044256,
      "overlap_weight": 0.044256
    },
    {
      "holding_symbol": "TSM",
      "left_weight": 0.091904,
      "right_weight": 0.041483,
      "overlap_weight": 0.041483
    }
  ]
}
