{
  "etf_id": "TW-00923",
  "ticker": "00923",
  "quote_symbol": "00923.TW",
  "name": "群益台ESG低碳50",
  "short_name": "群益ESG低碳50",
  "listing_market": "TW",
  "listing_exchange": "TWSE",
  "currency": "TWD",
  "benchmark_symbol": "0050.TW",
  "benchmark_name": null,
  "issuer": null,
  "asset_class": null,
  "is_thematic": false,
  "active": true,
  "name_en": "群益台ESG低碳50",
  "short_name_en": "群益ESG低碳50",
  "name_zh": null,
  "short_name_zh": null,
  "display_name": "群益台ESG低碳50",
  "display_short_name": "群益ESG低碳50",
  "classifications": [
    {
      "dimension": "asset_class",
      "code": "equity"
    },
    {
      "dimension": "geography",
      "code": "taiwan"
    },
    {
      "dimension": "listing_market",
      "code": "tw"
    },
    {
      "dimension": "management_style",
      "code": "passive"
    },
    {
      "dimension": "strategy",
      "code": "esg"
    }
  ],
  "metrics": {
    "total_return_1y": {
      "value": 91.6939,
      "unit": "percent"
    },
    "annualized_return": {
      "value": 91.6939,
      "unit": "percent"
    },
    "annualized_volatility": {
      "value": 27.3978,
      "unit": "percent"
    },
    "sharpe_ratio": {
      "value": 3.292,
      "unit": "ratio"
    },
    "max_drawdown": {
      "value": -15.3278,
      "unit": "percent"
    },
    "alpha": {
      "value": -9.7782,
      "unit": "percent"
    },
    "beta": {
      "value": 0.9973,
      "unit": "ratio"
    },
    "tracking_error": {
      "value": 9.2885,
      "unit": "percent"
    },
    "data_years": {
      "value": 2.9246,
      "unit": "years"
    }
  },
  "latest_price": {
    "date": "2026-07-22",
    "value": 41.08,
    "currency": "TWD"
  },
  "trend": [
    {
      "date": "2023-07-10",
      "value": 100.0
    },
    {
      "date": "2023-07-11",
      "value": 101.49
    },
    {
      "date": "2023-07-12",
      "value": 102.18
    },
    {
      "date": "2023-07-13",
      "value": 103.24
    },
    {
      "date": "2023-07-14",
      "value": 105.11
    },
    {
      "date": "2023-07-17",
      "value": 105.23
    },
    {
      "date": "2023-07-18",
      "value": 105.17
    },
    {
      "date": "2023-07-19",
      "value": 104.42
    },
    {
      "date": "2023-07-20",
      "value": 104.42
    },
    {
      "date": "2023-07-21",
      "value": 103.55
    },
    {
      "date": "2023-07-24",
      "value": 103.67
    },
    {
      "date": "2023-07-25",
      "value": 104.86
    },
    {
      "date": "2023-07-26",
      "value": 104.11
    },
    {
      "date": "2023-07-27",
      "value": 104.79
    },
    {
      "date": "2023-07-28",
      "value": 105.11
    },
    {
      "date": "2023-07-31",
      "value": 104.55
    },
    {
      "date": "2023-08-01",
      "value": 104.79
    },
    {
      "date": "2023-08-02",
      "value": 103.11
    },
    {
      "date": "2023-08-04",
      "value": 102.43
    },
    {
      "date": "2023-08-07",
      "value": 103.24
    },
    {
      "date": "2023-08-08",
      "value": 102.12
    },
    {
      "date": "2023-08-09",
      "value": 102.12
    },
    {
      "date": "2023-08-10",
      "value": 100.93
    },
    {
      "date": "2023-08-11",
      "value": 100.75
    },
    {
      "date": "2023-08-14",
      "value": 99.63
    },
    {
      "date": "2023-08-15",
      "value": 100.0
    },
    {
      "date": "2023-08-16",
      "value": 95.7
    },
    {
      "date": "2023-08-17",
      "value": 96.33
    },
    {
      "date": "2023-08-18",
      "value": 95.77
    },
    {
      "date": "2023-08-21",
      "value": 95.7
    },
    {
      "date": "2023-08-22",
      "value": 96.08
    },
    {
      "date": "2023-08-23",
      "value": 96.95
    },
    {
      "date": "2023-08-24",
      "value": 98.57
    },
    {
      "date": "2023-08-25",
      "value": 97.26
    },
    {
      "date": "2023-08-28",
      "value": 97.57
    },
    {
      "date": "2023-08-29",
      "value": 97.95
    },
    {
      "date": "2023-08-30",
      "value": 98.51
    },
    {
      "date": "2023-08-31",
      "value": 97.88
    },
    {
      "date": "2023-09-01",
      "value": 97.82
    },
    {
      "date": "2023-09-04",
      "value": 98.26
    },
    {
      "date": "2023-09-05",
      "value": 98.44
    },
    {
      "date": "2023-09-06",
      "value": 98.32
    },
    {
      "date": "2023-09-07",
      "value": 97.7
    },
    {
      "date": "2023-09-08",
      "value": 97.32
    },
    {
      "date": "2023-09-11",
      "value": 96.58
    },
    {
      "date": "2023-09-12",
      "value": 97.2
    },
    {
      "date": "2023-09-13",
      "value": 97.26
    },
    {
      "date": "2023-09-14",
      "value": 98.51
    },
    {
      "date": "2023-09-15",
      "value": 99.07
    },
    {
      "date": "2023-09-18",
      "value": 98.19
    },
    {
      "date": "2023-09-19",
      "value": 98.07
    },
    {
      "date": "2023-09-20",
      "value": 97.26
    },
    {
      "date": "2023-09-21",
      "value": 95.89
    },
    {
      "date": "2023-09-22",
      "value": 95.95
    },
    {
      "date": "2023-09-25",
      "value": 96.58
    },
    {
      "date": "2023-09-26",
      "value": 95.52
    },
    {
      "date": "2023-09-27",
      "value": 95.27
    },
    {
      "date": "2023-09-28",
      "value": 95.64
    },
    {
      "date": "2023-10-02",
      "value": 96.95
    },
    {
      "date": "2023-10-03",
      "value": 96.7
    },
    {
      "date": "2023-10-04",
      "value": 95.7
    },
    {
      "date": "2023-10-05",
      "value": 96.89
    },
    {
      "date": "2023-10-06",
      "value": 97.14
    },
    {
      "date": "2023-10-11",
      "value": 98.88
    },
    {
      "date": "2023-10-12",
      "value": 99.69
    },
    {
      "date": "2023-10-13",
      "value": 99.69
    },
    {
      "date": "2023-10-16",
      "value": 99.19
    },
    {
      "date": "2023-10-17",
      "value": 99.13
    },
    {
      "date": "2023-10-18",
      "value": 98.07
    },
    {
      "date": "2023-10-19",
      "value": 98.26
    },
    {
      "date": "2023-10-20",
      "value": 98.26
    },
    {
      "date": "2023-10-23",
      "value": 96.76
    },
    {
      "date": "2023-10-24",
      "value": 96.82
    },
    {
      "date": "2023-10-25",
      "value": 97.14
    },
    {
      "date": "2023-10-26",
      "value": 95.45
    },
    {
      "date": "2023-10-27",
      "value": 95.95
    },
    {
      "date": "2023-10-30",
      "value": 96.2
    },
    {
      "date": "2023-10-31",
      "value": 95.52
    },
    {
      "date": "2023-11-01",
      "value": 96.26
    },
    {
      "date": "2023-11-02",
      "value": 98.07
    },
    {
      "date": "2023-11-03",
      "value": 98.69
    },
    {
      "date": "2023-11-06",
      "value": 99.63
    },
    {
      "date": "2023-11-07",
      "value": 99.56
    },
    {
      "date": "2023-11-08",
      "value": 100.06
    },
    {
      "date": "2023-11-09",
      "value": 100.19
    },
    {
      "date": "2023-11-10",
      "value": 99.75
    },
    {
      "date": "2023-11-13",
      "value": 101.25
    },
    {
      "date": "2023-11-14",
      "value": 101.62
    },
    {
      "date": "2023-11-15",
      "value": 102.43
    },
    {
      "date": "2023-11-16",
      "value": 102.37
    },
    {
      "date": "2023-11-17",
      "value": 103.3
    },
    {
      "date": "2023-11-20",
      "value": 102.99
    },
    {
      "date": "2023-11-21",
      "value": 104.17
    },
    {
      "date": "2023-11-22",
      "value": 103.8
    },
    {
      "date": "2023-11-23",
      "value": 103.61
    },
    {
      "date": "2023-11-24",
      "value": 103.61
    },
    {
      "date": "2023-11-27",
      "value": 102.99
    },
    {
      "date": "2023-11-28",
      "value": 103.74
    },
    {
      "date": "2023-11-29",
      "value": 103.74
    },
    {
      "date": "2023-11-30",
      "value": 103.99
    },
    {
      "date": "2023-12-01",
      "value": 104.05
    },
    {
      "date": "2023-12-04",
      "value": 103.92
    },
    {
      "date": "2023-12-05",
      "value": 103.3
    },
    {
      "date": "2023-12-06",
      "value": 103.8
    },
    {
      "date": "2023-12-07",
      "value": 103.18
    },
    {
      "date": "2023-12-08",
      "value": 104.11
    },
    {
      "date": "2023-12-11",
      "value": 104.17
    },
    {
      "date": "2023-12-12",
      "value": 104.48
    },
    {
      "date": "2023-12-13",
      "value": 104.86
    },
    {
      "date": "2023-12-14",
      "value": 105.98
    },
    {
      "date": "2023-12-15",
      "value": 106.23
    },
    {
      "date": "2023-12-18",
      "value": 106.23
    },
    {
      "date": "2023-12-19",
      "value": 105.6
    },
    {
      "date": "2023-12-20",
      "value": 105.98
    },
    {
      "date": "2023-12-21",
      "value": 104.98
    },
    {
      "date": "2023-12-22",
      "value": 105.6
    },
    {
      "date": "2023-12-25",
      "value": 106.04
    },
    {
      "date": "2023-12-26",
      "value": 106.91
    },
    {
      "date": "2023-12-27",
      "value": 108.03
    },
    {
      "date": "2023-12-28",
      "value": 107.91
    },
    {
      "date": "2023-12-29",
      "value": 108.03
    },
    {
      "date": "2024-01-02",
      "value": 107.1
    },
    {
      "date": "2024-01-03",
      "value": 105.35
    },
    {
      "date": "2024-01-04",
      "value": 105.11
    },
    {
      "date": "2024-01-05",
      "value": 104.92
    },
    {
      "date": "2024-01-08",
      "value": 105.35
    },
    {
      "date": "2024-01-09",
      "value": 105.29
    },
    {
      "date": "2024-01-10",
      "value": 105.11
    },
    {
      "date": "2024-01-11",
      "value": 105.67
    },
    {
      "date": "2024-01-12",
      "value": 105.35
    },
    {
      "date": "2024-01-15",
      "value": 105.73
    },
    {
      "date": "2024-01-16",
      "value": 104.92
    },
    {
      "date": "2024-01-17",
      "value": 103.74
    },
    {
      "date": "2024-01-18",
      "value": 104.11
    },
    {
      "date": "2024-01-19",
      "value": 107.04
    },
    {
      "date": "2024-01-22",
      "value": 107.91
    },
    {
      "date": "2024-01-23",
      "value": 108.03
    },
    {
      "date": "2024-01-24",
      "value": 107.97
    },
    {
      "date": "2024-01-25",
      "value": 108.9
    },
    {
      "date": "2024-01-26",
      "value": 108.47
    },
    {
      "date": "2024-01-29",
      "value": 109.09
    },
    {
      "date": "2024-01-30",
      "value": 109.15
    },
    {
      "date": "2024-01-31",
      "value": 108.22
    },
    {
      "date": "2024-02-01",
      "value": 107.78
    },
    {
      "date": "2024-02-02",
      "value": 108.47
    },
    {
      "date": "2024-02-05",
      "value": 108.47
    },
    {
      "date": "2024-02-15",
      "value": 112.27
    },
    {
      "date": "2024-02-16",
      "value": 112.14
    },
    {
      "date": "2024-02-19",
      "value": 112.33
    },
    {
      "date": "2024-02-20",
      "value": 113.33
    },
    {
      "date": "2024-02-21",
      "value": 112.83
    },
    {
      "date": "2024-02-22",
      "value": 114.07
    },
    {
      "date": "2024-02-23",
      "value": 115.13
    },
    {
      "date": "2024-02-26",
      "value": 115.44
    },
    {
      "date": "2024-02-27",
      "value": 114.01
    },
    {
      "date": "2024-02-29",
      "value": 114.51
    },
    {
      "date": "2024-03-01",
      "value": 114.07
    },
    {
      "date": "2024-03-04",
      "value": 116.38
    },
    {
      "date": "2024-03-05",
      "value": 117.43
    },
    {
      "date": "2024-03-06",
      "value": 118.18
    },
    {
      "date": "2024-03-07",
      "value": 120.73
    },
    {
      "date": "2024-03-08",
      "value": 121.48
    },
    {
      "date": "2024-03-11",
      "value": 120.73
    },
    {
      "date": "2024-03-12",
      "value": 121.92
    },
    {
      "date": "2024-03-13",
      "value": 122.17
    },
    {
      "date": "2024-03-14",
      "value": 121.36
    },
    {
      "date": "2024-03-15",
      "value": 120.73
    },
    {
      "date": "2024-03-18",
      "value": 121.61
    },
    {
      "date": "2024-03-19",
      "value": 121.92
    },
    {
      "date": "2024-03-20",
      "value": 121.11
    },
    {
      "date": "2024-03-21",
      "value": 123.35
    },
    {
      "date": "2024-03-22",
      "value": 123.47
    },
    {
      "date": "2024-03-25",
      "value": 123.35
    },
    {
      "date": "2024-03-26",
      "value": 122.85
    },
    {
      "date": "2024-03-27",
      "value": 123.29
    },
    {
      "date": "2024-03-28",
      "value": 123.04
    },
    {
      "date": "2024-03-29",
      "value": 123.85
    },
    {
      "date": "2024-04-01",
      "value": 122.98
    },
    {
      "date": "2024-04-02",
      "value": 124.47
    },
    {
      "date": "2024-04-03",
      "value": 124.03
    },
    {
      "date": "2024-04-08",
      "value": 124.22
    },
    {
      "date": "2024-04-09",
      "value": 126.21
    },
    {
      "date": "2024-04-10",
      "value": 126.4
    },
    {
      "date": "2024-04-11",
      "value": 125.97
    },
    {
      "date": "2024-04-12",
      "value": 125.65
    },
    {
      "date": "2024-04-15",
      "value": 123.91
    },
    {
      "date": "2024-04-16",
      "value": 120.86
    },
    {
      "date": "2024-04-17",
      "value": 122.1
    },
    {
      "date": "2024-04-18",
      "value": 122.48
    },
    {
      "date": "2024-04-19",
      "value": 117.56
    },
    {
      "date": "2024-04-22",
      "value": 115.82
    },
    {
      "date": "2024-04-23",
      "value": 116.87
    },
    {
      "date": "2024-04-24",
      "value": 120.3
    },
    {
      "date": "2024-04-25",
      "value": 118.43
    },
    {
      "date": "2024-04-26",
      "value": 120.17
    },
    {
      "date": "2024-04-29",
      "value": 122.29
    },
    {
      "date": "2024-04-30",
      "value": 122.23
    },
    {
      "date": "2024-05-02",
      "value": 121.05
    },
    {
      "date": "2024-05-03",
      "value": 121.54
    },
    {
      "date": "2024-05-06",
      "value": 123.41
    },
    {
      "date": "2024-05-07",
      "value": 123.91
    },
    {
      "date": "2024-05-08",
      "value": 124.28
    },
    {
      "date": "2024-05-09",
      "value": 124.03
    },
    {
      "date": "2024-05-10",
      "value": 124.41
    },
    {
      "date": "2024-05-13",
      "value": 125.16
    },
    {
      "date": "2024-05-14",
      "value": 126.28
    },
    {
      "date": "2024-05-15",
      "value": 127.46
    },
    {
      "date": "2024-05-16",
      "value": 128.33
    },
    {
      "date": "2024-05-17",
      "value": 128.21
    },
    {
      "date": "2024-05-20",
      "value": 128.46
    },
    {
      "date": "2024-05-21",
      "value": 128.27
    },
    {
      "date": "2024-05-22",
      "value": 130.45
    },
    {
      "date": "2024-05-23",
      "value": 131.38
    },
    {
      "date": "2024-05-24",
      "value": 131.13
    },
    {
      "date": "2024-05-27",
      "value": 133.75
    },
    {
      "date": "2024-05-28",
      "value": 134.0
    },
    {
      "date": "2024-05-29",
      "value": 133.06
    },
    {
      "date": "2024-05-30",
      "value": 131.07
    },
    {
      "date": "2024-05-31",
      "value": 129.27
    },
    {
      "date": "2024-06-03",
      "value": 132.0
    },
    {
      "date": "2024-06-04",
      "value": 130.2
    },
    {
      "date": "2024-06-05",
      "value": 131.01
    },
    {
      "date": "2024-06-06",
      "value": 133.56
    },
    {
      "date": "2024-06-07",
      "value": 133.25
    },
    {
      "date": "2024-06-11",
      "value": 133.62
    },
    {
      "date": "2024-06-12",
      "value": 135.49
    },
    {
      "date": "2024-06-13",
      "value": 137.86
    },
    {
      "date": "2024-06-14",
      "value": 138.67
    },
    {
      "date": "2024-06-17",
      "value": 138.67
    },
    {
      "date": "2024-06-18",
      "value": 140.91
    },
    {
      "date": "2024-06-19",
      "value": 144.33
    },
    {
      "date": "2024-06-20",
      "value": 145.27
    },
    {
      "date": "2024-06-21",
      "value": 144.65
    },
    {
      "date": "2024-06-24",
      "value": 141.53
    },
    {
      "date": "2024-06-25",
      "value": 141.1
    },
    {
      "date": "2024-06-26",
      "value": 141.66
    },
    {
      "date": "2024-06-27",
      "value": 141.28
    },
    {
      "date": "2024-06-28",
      "value": 142.4
    },
    {
      "date": "2024-07-01",
      "value": 142.53
    },
    {
      "date": "2024-07-02",
      "value": 141.22
    },
    {
      "date": "2024-07-03",
      "value": 142.96
    },
    {
      "date": "2024-07-04",
      "value": 145.7
    },
    {
      "date": "2024-07-05",
      "value": 145.7
    },
    {
      "date": "2024-07-08",
      "value": 148.75
    },
    {
      "date": "2024-07-09",
      "value": 149.81
    },
    {
      "date": "2024-07-10",
      "value": 150.06
    },
    {
      "date": "2024-07-11",
      "value": 152.3
    },
    {
      "date": "2024-07-12",
      "value": 148.63
    },
    {
      "date": "2024-07-15",
      "value": 148.63
    },
    {
      "date": "2024-07-16",
      "value": 149.13
    },
    {
      "date": "2024-07-17",
      "value": 147.32
    },
    {
      "date": "2024-07-18",
      "value": 144.4
    },
    {
      "date": "2024-07-19",
      "value": 141.72
    },
    {
      "date": "2024-07-22",
      "value": 137.67
    },
    {
      "date": "2024-07-23",
      "value": 141.03
    },
    {
      "date": "2024-07-26",
      "value": 136.74
    },
    {
      "date": "2024-07-29",
      "value": 135.8
    },
    {
      "date": "2024-07-30",
      "value": 135.49
    },
    {
      "date": "2024-07-31",
      "value": 135.55
    },
    {
      "date": "2024-08-01",
      "value": 137.61
    },
    {
      "date": "2024-08-02",
      "value": 131.32
    },
    {
      "date": "2024-08-05",
      "value": 120.05
    },
    {
      "date": "2024-08-06",
      "value": 124.6
    },
    {
      "date": "2024-08-07",
      "value": 129.58
    },
    {
      "date": "2024-08-08",
      "value": 127.27
    },
    {
      "date": "2024-08-09",
      "value": 130.7
    },
    {
      "date": "2024-08-12",
      "value": 132.81
    },
    {
      "date": "2024-08-13",
      "value": 133.75
    },
    {
      "date": "2024-08-14",
      "value": 135.55
    },
    {
      "date": "2024-08-15",
      "value": 134.56
    },
    {
      "date": "2024-08-16",
      "value": 137.55
    },
    {
      "date": "2024-08-19",
      "value": 138.29
    },
    {
      "date": "2024-08-20",
      "value": 138.36
    },
    {
      "date": "2024-08-21",
      "value": 131.01
    },
    {
      "date": "2024-08-22",
      "value": 130.26
    },
    {
      "date": "2024-08-23",
      "value": 130.26
    },
    {
      "date": "2024-08-26",
      "value": 130.39
    },
    {
      "date": "2024-08-27",
      "value": 129.76
    },
    {
      "date": "2024-08-28",
      "value": 130.95
    },
    {
      "date": "2024-08-29",
      "value": 130.39
    },
    {
      "date": "2024-08-30",
      "value": 130.7
    },
    {
      "date": "2024-09-02",
      "value": 130.39
    },
    {
      "date": "2024-09-03",
      "value": 129.89
    },
    {
      "date": "2024-09-04",
      "value": 124.35
    },
    {
      "date": "2024-09-05",
      "value": 124.1
    },
    {
      "date": "2024-09-06",
      "value": 125.59
    },
    {
      "date": "2024-09-09",
      "value": 123.85
    },
    {
      "date": "2024-09-10",
      "value": 123.79
    },
    {
      "date": "2024-09-11",
      "value": 123.66
    },
    {
      "date": "2024-09-12",
      "value": 127.4
    },
    {
      "date": "2024-09-13",
      "value": 127.4
    },
    {
      "date": "2024-09-16",
      "value": 127.52
    },
    {
      "date": "2024-09-18",
      "value": 126.34
    },
    {
      "date": "2024-09-19",
      "value": 127.83
    },
    {
      "date": "2024-09-20",
      "value": 128.89
    },
    {
      "date": "2024-09-23",
      "value": 129.83
    },
    {
      "date": "2024-09-24",
      "value": 130.76
    },
    {
      "date": "2024-09-25",
      "value": 132.94
    },
    {
      "date": "2024-09-26",
      "value": 133.87
    },
    {
      "date": "2024-09-27",
      "value": 133.62
    },
    {
      "date": "2024-09-30",
      "value": 130.32
    },
    {
      "date": "2024-10-01",
      "value": 130.26
    },
    {
      "date": "2024-10-04",
      "value": 129.95
    },
    {
      "date": "2024-10-07",
      "value": 132.07
    },
    {
      "date": "2024-10-08",
      "value": 131.01
    },
    {
      "date": "2024-10-09",
      "value": 132.32
    },
    {
      "date": "2024-10-11",
      "value": 133.81
    },
    {
      "date": "2024-10-14",
      "value": 134.43
    },
    {
      "date": "2024-10-15",
      "value": 136.86
    },
    {
      "date": "2024-10-16",
      "value": 135.18
    },
    {
      "date": "2024-10-17",
      "value": 135.43
    },
    {
      "date": "2024-10-18",
      "value": 137.05
    },
    {
      "date": "2024-10-21",
      "value": 137.3
    },
    {
      "date": "2024-10-22",
      "value": 137.36
    },
    {
      "date": "2024-10-23",
      "value": 136.55
    },
    {
      "date": "2024-10-24",
      "value": 135.8
    },
    {
      "date": "2024-10-25",
      "value": 136.86
    },
    {
      "date": "2024-10-28",
      "value": 136.55
    },
    {
      "date": "2024-10-29",
      "value": 134.0
    },
    {
      "date": "2024-10-30",
      "value": 133.87
    },
    {
      "date": "2024-11-01",
      "value": 133.19
    },
    {
      "date": "2024-11-04",
      "value": 134.06
    },
    {
      "date": "2024-11-05",
      "value": 133.87
    },
    {
      "date": "2024-11-06",
      "value": 135.06
    },
    {
      "date": "2024-11-07",
      "value": 136.3
    },
    {
      "date": "2024-11-08",
      "value": 136.8
    },
    {
      "date": "2024-11-11",
      "value": 136.99
    },
    {
      "date": "2024-11-12",
      "value": 134.12
    },
    {
      "date": "2024-11-13",
      "value": 134.0
    },
    {
      "date": "2024-11-14",
      "value": 132.69
    },
    {
      "date": "2024-11-15",
      "value": 133.25
    },
    {
      "date": "2024-11-18",
      "value": 131.94
    },
    {
      "date": "2024-11-19",
      "value": 133.56
    },
    {
      "date": "2024-11-20",
      "value": 133.0
    },
    {
      "date": "2024-11-21",
      "value": 132.07
    },
    {
      "date": "2024-11-22",
      "value": 133.75
    },
    {
      "date": "2024-11-25",
      "value": 134.0
    },
    {
      "date": "2024-11-26",
      "value": 132.25
    },
    {
      "date": "2024-11-27",
      "value": 130.51
    },
    {
      "date": "2024-11-28",
      "value": 130.07
    },
    {
      "date": "2024-11-29",
      "value": 130.32
    },
    {
      "date": "2024-12-02",
      "value": 133.31
    },
    {
      "date": "2024-12-03",
      "value": 134.18
    },
    {
      "date": "2024-12-04",
      "value": 135.18
    },
    {
      "date": "2024-12-05",
      "value": 135.62
    },
    {
      "date": "2024-12-06",
      "value": 135.55
    },
    {
      "date": "2024-12-09",
      "value": 135.55
    },
    {
      "date": "2024-12-10",
      "value": 135.12
    },
    {
      "date": "2024-12-11",
      "value": 134.31
    },
    {
      "date": "2024-12-12",
      "value": 135.31
    },
    {
      "date": "2024-12-13",
      "value": 135.49
    },
    {
      "date": "2024-12-16",
      "value": 135.43
    },
    {
      "date": "2024-12-17",
      "value": 136.24
    },
    {
      "date": "2024-12-18",
      "value": 136.36
    },
    {
      "date": "2024-12-19",
      "value": 135.31
    },
    {
      "date": "2024-12-20",
      "value": 134.43
    },
    {
      "date": "2024-12-23",
      "value": 136.67
    },
    {
      "date": "2024-12-24",
      "value": 137.05
    },
    {
      "date": "2024-12-25",
      "value": 137.55
    },
    {
      "date": "2024-12-26",
      "value": 137.67
    },
    {
      "date": "2024-12-27",
      "value": 137.86
    },
    {
      "date": "2024-12-30",
      "value": 137.55
    },
    {
      "date": "2024-12-31",
      "value": 136.92
    },
    {
      "date": "2025-01-02",
      "value": 134.99
    },
    {
      "date": "2025-01-03",
      "value": 135.8
    },
    {
      "date": "2025-01-06",
      "value": 138.85
    },
    {
      "date": "2025-01-07",
      "value": 140.85
    },
    {
      "date": "2025-01-08",
      "value": 139.66
    },
    {
      "date": "2025-01-09",
      "value": 137.55
    },
    {
      "date": "2025-01-10",
      "value": 137.55
    },
    {
      "date": "2025-01-13",
      "value": 134.25
    },
    {
      "date": "2025-01-14",
      "value": 135.37
    },
    {
      "date": "2025-01-15",
      "value": 134.43
    },
    {
      "date": "2025-01-16",
      "value": 136.86
    },
    {
      "date": "2025-01-17",
      "value": 137.24
    },
    {
      "date": "2025-01-20",
      "value": 138.61
    },
    {
      "date": "2025-01-21",
      "value": 139.29
    },
    {
      "date": "2025-01-22",
      "value": 140.16
    },
    {
      "date": "2025-02-03",
      "value": 135.74
    },
    {
      "date": "2025-02-04",
      "value": 136.36
    },
    {
      "date": "2025-02-05",
      "value": 138.61
    },
    {
      "date": "2025-02-06",
      "value": 138.73
    },
    {
      "date": "2025-02-07",
      "value": 139.91
    },
    {
      "date": "2025-02-10",
      "value": 138.85
    },
    {
      "date": "2025-02-11",
      "value": 139.66
    },
    {
      "date": "2025-02-12",
      "value": 139.29
    },
    {
      "date": "2025-02-13",
      "value": 139.73
    },
    {
      "date": "2025-02-14",
      "value": 138.73
    },
    {
      "date": "2025-02-17",
      "value": 140.41
    },
    {
      "date": "2025-02-18",
      "value": 135.93
    },
    {
      "date": "2025-02-19",
      "value": 135.8
    },
    {
      "date": "2025-02-20",
      "value": 135.43
    },
    {
      "date": "2025-02-21",
      "value": 136.43
    },
    {
      "date": "2025-02-24",
      "value": 135.8
    },
    {
      "date": "2025-02-25",
      "value": 134.62
    },
    {
      "date": "2025-02-26",
      "value": 135.24
    },
    {
      "date": "2025-02-27",
      "value": 133.62
    },
    {
      "date": "2025-03-03",
      "value": 131.38
    },
    {
      "date": "2025-03-04",
      "value": 130.7
    },
    {
      "date": "2025-03-05",
      "value": 132.0
    },
    {
      "date": "2025-03-06",
      "value": 131.51
    },
    {
      "date": "2025-03-07",
      "value": 130.2
    },
    {
      "date": "2025-03-10",
      "value": 129.45
    },
    {
      "date": "2025-03-11",
      "value": 127.46
    },
    {
      "date": "2025-03-12",
      "value": 127.96
    },
    {
      "date": "2025-03-13",
      "value": 127.21
    },
    {
      "date": "2025-03-14",
      "value": 126.71
    },
    {
      "date": "2025-03-17",
      "value": 127.58
    },
    {
      "date": "2025-03-18",
      "value": 128.89
    },
    {
      "date": "2025-03-19",
      "value": 127.71
    },
    {
      "date": "2025-03-20",
      "value": 129.58
    },
    {
      "date": "2025-03-21",
      "value": 128.77
    },
    {
      "date": "2025-03-24",
      "value": 128.46
    },
    {
      "date": "2025-03-25",
      "value": 129.83
    },
    {
      "date": "2025-03-26",
      "value": 129.76
    },
    {
      "date": "2025-03-27",
      "value": 127.77
    },
    {
      "date": "2025-03-28",
      "value": 126.28
    },
    {
      "date": "2025-03-31",
      "value": 122.35
    },
    {
      "date": "2025-04-01",
      "value": 124.47
    },
    {
      "date": "2025-04-02",
      "value": 124.22
    },
    {
      "date": "2025-04-07",
      "value": 111.83
    },
    {
      "date": "2025-04-08",
      "value": 108.22
    },
    {
      "date": "2025-04-09",
      "value": 102.49
    },
    {
      "date": "2025-04-10",
      "value": 112.7
    },
    {
      "date": "2025-04-11",
      "value": 115.38
    },
    {
      "date": "2025-04-14",
      "value": 115.32
    },
    {
      "date": "2025-04-15",
      "value": 116.31
    },
    {
      "date": "2025-04-16",
      "value": 114.63
    },
    {
      "date": "2025-04-17",
      "value": 113.82
    },
    {
      "date": "2025-04-18",
      "value": 114.07
    },
    {
      "date": "2025-04-21",
      "value": 112.7
    },
    {
      "date": "2025-04-22",
      "value": 111.33
    },
    {
      "date": "2025-04-23",
      "value": 115.26
    },
    {
      "date": "2025-04-24",
      "value": 114.2
    },
    {
      "date": "2025-04-25",
      "value": 117.19
    },
    {
      "date": "2025-04-28",
      "value": 117.75
    },
    {
      "date": "2025-04-29",
      "value": 118.18
    },
    {
      "date": "2025-04-30",
      "value": 118.24
    },
    {
      "date": "2025-05-02",
      "value": 120.11
    },
    {
      "date": "2025-05-05",
      "value": 118.99
    },
    {
      "date": "2025-05-06",
      "value": 118.68
    },
    {
      "date": "2025-05-07",
      "value": 118.8
    },
    {
      "date": "2025-05-08",
      "value": 119.68
    },
    {
      "date": "2025-05-09",
      "value": 120.98
    },
    {
      "date": "2025-05-12",
      "value": 122.17
    },
    {
      "date": "2025-05-13",
      "value": 124.03
    },
    {
      "date": "2025-05-14",
      "value": 126.15
    },
    {
      "date": "2025-05-15",
      "value": 126.15
    },
    {
      "date": "2025-05-16",
      "value": 126.09
    },
    {
      "date": "2025-05-19",
      "value": 124.22
    },
    {
      "date": "2025-05-20",
      "value": 124.72
    },
    {
      "date": "2025-05-21",
      "value": 126.28
    },
    {
      "date": "2025-05-22",
      "value": 125.28
    },
    {
      "date": "2025-05-23",
      "value": 124.53
    },
    {
      "date": "2025-05-26",
      "value": 124.22
    },
    {
      "date": "2025-05-27",
      "value": 123.29
    },
    {
      "date": "2025-05-28",
      "value": 123.91
    },
    {
      "date": "2025-05-29",
      "value": 123.97
    },
    {
      "date": "2025-06-02",
      "value": 121.48
    },
    {
      "date": "2025-06-03",
      "value": 122.6
    },
    {
      "date": "2025-06-04",
      "value": 124.47
    },
    {
      "date": "2025-06-05",
      "value": 124.6
    },
    {
      "date": "2025-06-06",
      "value": 124.72
    },
    {
      "date": "2025-06-09",
      "value": 125.72
    },
    {
      "date": "2025-06-10",
      "value": 128.46
    },
    {
      "date": "2025-06-11",
      "value": 129.58
    },
    {
      "date": "2025-06-12",
      "value": 128.83
    },
    {
      "date": "2025-06-13",
      "value": 127.9
    },
    {
      "date": "2025-06-16",
      "value": 128.02
    },
    {
      "date": "2025-06-17",
      "value": 128.64
    },
    {
      "date": "2025-06-18",
      "value": 129.58
    },
    {
      "date": "2025-06-19",
      "value": 128.46
    },
    {
      "date": "2025-06-20",
      "value": 127.96
    },
    {
      "date": "2025-06-23",
      "value": 127.65
    },
    {
      "date": "2025-06-24",
      "value": 129.64
    },
    {
      "date": "2025-06-25",
      "value": 131.13
    },
    {
      "date": "2025-06-26",
      "value": 131.07
    },
    {
      "date": "2025-06-27",
      "value": 131.26
    },
    {
      "date": "2025-06-30",
      "value": 131.13
    },
    {
      "date": "2025-07-01",
      "value": 131.69
    },
    {
      "date": "2025-07-02",
      "value": 132.25
    },
    {
      "date": "2025-07-03",
      "value": 133.37
    },
    {
      "date": "2025-07-04",
      "value": 132.88
    },
    {
      "date": "2025-07-07",
      "value": 132.25
    },
    {
      "date": "2025-07-08",
      "value": 131.44
    },
    {
      "date": "2025-07-09",
      "value": 133.44
    },
    {
      "date": "2025-07-10",
      "value": 134.81
    },
    {
      "date": "2025-07-11",
      "value": 135.18
    },
    {
      "date": "2025-07-14",
      "value": 134.12
    },
    {
      "date": "2025-07-15",
      "value": 135.55
    },
    {
      "date": "2025-07-16",
      "value": 136.74
    },
    {
      "date": "2025-07-17",
      "value": 136.8
    },
    {
      "date": "2025-07-18",
      "value": 138.04
    },
    {
      "date": "2025-07-21",
      "value": 137.67
    },
    {
      "date": "2025-07-22",
      "value": 136.86
    },
    {
      "date": "2025-07-23",
      "value": 137.67
    },
    {
      "date": "2025-07-24",
      "value": 138.23
    },
    {
      "date": "2025-07-25",
      "value": 137.92
    },
    {
      "date": "2025-07-28",
      "value": 138.11
    },
    {
      "date": "2025-07-29",
      "value": 136.67
    },
    {
      "date": "2025-07-30",
      "value": 137.24
    },
    {
      "date": "2025-07-31",
      "value": 138.11
    },
    {
      "date": "2025-08-01",
      "value": 137.05
    },
    {
      "date": "2025-08-04",
      "value": 136.55
    },
    {
      "date": "2025-08-05",
      "value": 138.17
    },
    {
      "date": "2025-08-06",
      "value": 137.05
    },
    {
      "date": "2025-08-07",
      "value": 139.17
    },
    {
      "date": "2025-08-08",
      "value": 139.29
    },
    {
      "date": "2025-08-11",
      "value": 139.98
    },
    {
      "date": "2025-08-12",
      "value": 140.04
    },
    {
      "date": "2025-08-13",
      "value": 140.72
    },
    {
      "date": "2025-08-14",
      "value": 140.72
    },
    {
      "date": "2025-08-15",
      "value": 141.03
    },
    {
      "date": "2025-08-18",
      "value": 135.74
    },
    {
      "date": "2025-08-19",
      "value": 135.12
    },
    {
      "date": "2025-08-20",
      "value": 131.94
    },
    {
      "date": "2025-08-21",
      "value": 132.63
    },
    {
      "date": "2025-08-22",
      "value": 132.13
    },
    {
      "date": "2025-08-25",
      "value": 134.37
    },
    {
      "date": "2025-08-26",
      "value": 134.43
    },
    {
      "date": "2025-08-27",
      "value": 135.31
    },
    {
      "date": "2025-08-28",
      "value": 134.31
    },
    {
      "date": "2025-08-29",
      "value": 133.87
    },
    {
      "date": "2025-09-01",
      "value": 132.88
    },
    {
      "date": "2025-09-02",
      "value": 133.25
    },
    {
      "date": "2025-09-03",
      "value": 133.37
    },
    {
      "date": "2025-09-04",
      "value": 133.81
    },
    {
      "date": "2025-09-05",
      "value": 135.18
    },
    {
      "date": "2025-09-08",
      "value": 136.99
    },
    {
      "date": "2025-09-09",
      "value": 138.23
    },
    {
      "date": "2025-09-10",
      "value": 140.1
    },
    {
      "date": "2025-09-11",
      "value": 140.78
    },
    {
      "date": "2025-09-12",
      "value": 141.66
    },
    {
      "date": "2025-09-15",
      "value": 141.59
    },
    {
      "date": "2025-09-16",
      "value": 143.46
    },
    {
      "date": "2025-09-17",
      "value": 142.47
    },
    {
      "date": "2025-09-18",
      "value": 143.96
    },
    {
      "date": "2025-09-19",
      "value": 144.08
    },
    {
      "date": "2025-09-22",
      "value": 144.27
    },
    {
      "date": "2025-09-23",
      "value": 146.08
    },
    {
      "date": "2025-09-24",
      "value": 145.77
    },
    {
      "date": "2025-09-25",
      "value": 145.39
    },
    {
      "date": "2025-09-26",
      "value": 143.09
    },
    {
      "date": "2025-09-30",
      "value": 144.27
    },
    {
      "date": "2025-10-01",
      "value": 144.27
    },
    {
      "date": "2025-10-02",
      "value": 146.58
    },
    {
      "date": "2025-10-03",
      "value": 149.07
    },
    {
      "date": "2025-10-07",
      "value": 151.93
    },
    {
      "date": "2025-10-08",
      "value": 151.0
    },
    {
      "date": "2025-10-09",
      "value": 152.05
    },
    {
      "date": "2025-10-13",
      "value": 150.19
    },
    {
      "date": "2025-10-14",
      "value": 149.32
    },
    {
      "date": "2025-10-15",
      "value": 151.93
    },
    {
      "date": "2025-10-16",
      "value": 154.67
    },
    {
      "date": "2025-10-17",
      "value": 153.11
    },
    {
      "date": "2025-10-20",
      "value": 155.42
    },
    {
      "date": "2025-10-21",
      "value": 156.1
    },
    {
      "date": "2025-10-22",
      "value": 155.48
    },
    {
      "date": "2025-10-23",
      "value": 154.42
    },
    {
      "date": "2025-10-27",
      "value": 158.16
    },
    {
      "date": "2025-10-28",
      "value": 157.72
    },
    {
      "date": "2025-10-29",
      "value": 160.15
    },
    {
      "date": "2025-10-30",
      "value": 160.21
    },
    {
      "date": "2025-10-31",
      "value": 160.77
    },
    {
      "date": "2025-11-03",
      "value": 159.34
    },
    {
      "date": "2025-11-04",
      "value": 158.59
    },
    {
      "date": "2025-11-05",
      "value": 156.97
    },
    {
      "date": "2025-11-06",
      "value": 157.78
    },
    {
      "date": "2025-11-07",
      "value": 155.48
    },
    {
      "date": "2025-11-10",
      "value": 157.29
    },
    {
      "date": "2025-11-11",
      "value": 156.35
    },
    {
      "date": "2025-11-12",
      "value": 157.04
    },
    {
      "date": "2025-11-13",
      "value": 156.41
    },
    {
      "date": "2025-11-14",
      "value": 153.11
    },
    {
      "date": "2025-11-17",
      "value": 153.05
    },
    {
      "date": "2025-11-18",
      "value": 149.63
    },
    {
      "date": "2025-11-19",
      "value": 148.88
    },
    {
      "date": "2025-11-20",
      "value": 153.61
    },
    {
      "date": "2025-11-21",
      "value": 148.63
    },
    {
      "date": "2025-11-24",
      "value": 148.51
    },
    {
      "date": "2025-11-25",
      "value": 150.06
    },
    {
      "date": "2025-11-26",
      "value": 152.93
    },
    {
      "date": "2025-11-27",
      "value": 154.67
    },
    {
      "date": "2025-11-28",
      "value": 155.54
    },
    {
      "date": "2025-12-01",
      "value": 153.92
    },
    {
      "date": "2025-12-02",
      "value": 154.11
    },
    {
      "date": "2025-12-03",
      "value": 155.42
    },
    {
      "date": "2025-12-04",
      "value": 155.29
    },
    {
      "date": "2025-12-05",
      "value": 156.54
    },
    {
      "date": "2025-12-08",
      "value": 158.16
    },
    {
      "date": "2025-12-09",
      "value": 158.03
    },
    {
      "date": "2025-12-10",
      "value": 159.4
    },
    {
      "date": "2025-12-11",
      "value": 157.47
    },
    {
      "date": "2025-12-12",
      "value": 157.78
    },
    {
      "date": "2025-12-15",
      "value": 155.98
    },
    {
      "date": "2025-12-16",
      "value": 154.36
    },
    {
      "date": "2025-12-17",
      "value": 153.99
    },
    {
      "date": "2025-12-18",
      "value": 153.8
    },
    {
      "date": "2025-12-19",
      "value": 155.35
    },
    {
      "date": "2025-12-22",
      "value": 157.85
    },
    {
      "date": "2025-12-23",
      "value": 158.16
    },
    {
      "date": "2025-12-24",
      "value": 158.41
    },
    {
      "date": "2025-12-26",
      "value": 159.4
    },
    {
      "date": "2025-12-29",
      "value": 161.15
    },
    {
      "date": "2025-12-30",
      "value": 161.02
    },
    {
      "date": "2025-12-31",
      "value": 161.89
    },
    {
      "date": "2026-01-02",
      "value": 164.45
    },
    {
      "date": "2026-01-05",
      "value": 169.55
    },
    {
      "date": "2026-01-06",
      "value": 171.79
    },
    {
      "date": "2026-01-07",
      "value": 170.49
    },
    {
      "date": "2026-01-08",
      "value": 169.99
    },
    {
      "date": "2026-01-09",
      "value": 169.74
    },
    {
      "date": "2026-01-12",
      "value": 170.73
    },
    {
      "date": "2026-01-13",
      "value": 171.48
    },
    {
      "date": "2026-01-14",
      "value": 172.6
    },
    {
      "date": "2026-01-15",
      "value": 171.86
    },
    {
      "date": "2026-01-16",
      "value": 175.28
    },
    {
      "date": "2026-01-19",
      "value": 175.72
    },
    {
      "date": "2026-01-20",
      "value": 176.28
    },
    {
      "date": "2026-01-21",
      "value": 174.53
    },
    {
      "date": "2026-01-22",
      "value": 177.27
    },
    {
      "date": "2026-01-23",
      "value": 179.14
    },
    {
      "date": "2026-01-26",
      "value": 179.7
    },
    {
      "date": "2026-01-27",
      "value": 181.76
    },
    {
      "date": "2026-01-28",
      "value": 184.06
    },
    {
      "date": "2026-01-29",
      "value": 182.69
    },
    {
      "date": "2026-01-30",
      "value": 179.95
    },
    {
      "date": "2026-02-02",
      "value": 176.9
    },
    {
      "date": "2026-02-03",
      "value": 181.44
    },
    {
      "date": "2026-02-04",
      "value": 181.76
    },
    {
      "date": "2026-02-05",
      "value": 178.83
    },
    {
      "date": "2026-02-06",
      "value": 178.52
    },
    {
      "date": "2026-02-09",
      "value": 183.56
    },
    {
      "date": "2026-02-10",
      "value": 187.48
    },
    {
      "date": "2026-02-11",
      "value": 191.34
    },
    {
      "date": "2026-02-23",
      "value": 191.72
    },
    {
      "date": "2026-02-24",
      "value": 197.14
    },
    {
      "date": "2026-02-25",
      "value": 202.3
    },
    {
      "date": "2026-02-26",
      "value": 191.59
    },
    {
      "date": "2026-03-02",
      "value": 188.98
    },
    {
      "date": "2026-03-03",
      "value": 184.0
    },
    {
      "date": "2026-03-04",
      "value": 176.03
    },
    {
      "date": "2026-03-05",
      "value": 180.57
    },
    {
      "date": "2026-03-06",
      "value": 180.14
    },
    {
      "date": "2026-03-09",
      "value": 171.3
    },
    {
      "date": "2026-03-10",
      "value": 175.9
    },
    {
      "date": "2026-03-11",
      "value": 182.69
    },
    {
      "date": "2026-03-12",
      "value": 180.45
    },
    {
      "date": "2026-03-13",
      "value": 179.33
    },
    {
      "date": "2026-03-16",
      "value": 178.95
    },
    {
      "date": "2026-03-17",
      "value": 181.07
    },
    {
      "date": "2026-03-18",
      "value": 183.69
    },
    {
      "date": "2026-03-19",
      "value": 180.76
    },
    {
      "date": "2026-03-20",
      "value": 180.14
    },
    {
      "date": "2026-03-23",
      "value": 176.15
    },
    {
      "date": "2026-03-24",
      "value": 176.21
    },
    {
      "date": "2026-03-25",
      "value": 181.26
    },
    {
      "date": "2026-03-26",
      "value": 180.51
    },
    {
      "date": "2026-03-27",
      "value": 179.45
    },
    {
      "date": "2026-03-30",
      "value": 176.03
    },
    {
      "date": "2026-03-31",
      "value": 171.36
    },
    {
      "date": "2026-04-01",
      "value": 179.02
    },
    {
      "date": "2026-04-02",
      "value": 175.65
    },
    {
      "date": "2026-04-07",
      "value": 178.33
    },
    {
      "date": "2026-04-08",
      "value": 188.04
    },
    {
      "date": "2026-04-09",
      "value": 188.73
    },
    {
      "date": "2026-04-10",
      "value": 192.4
    },
    {
      "date": "2026-04-13",
      "value": 192.47
    },
    {
      "date": "2026-04-14",
      "value": 197.45
    },
    {
      "date": "2026-04-15",
      "value": 200.81
    },
    {
      "date": "2026-04-16",
      "value": 203.74
    },
    {
      "date": "2026-04-17",
      "value": 202.43
    },
    {
      "date": "2026-04-20",
      "value": 204.36
    },
    {
      "date": "2026-04-21",
      "value": 207.91
    },
    {
      "date": "2026-04-22",
      "value": 210.46
    },
    {
      "date": "2026-04-23",
      "value": 210.02
    },
    {
      "date": "2026-04-24",
      "value": 217.87
    },
    {
      "date": "2026-04-27",
      "value": 223.47
    },
    {
      "date": "2026-04-28",
      "value": 222.42
    },
    {
      "date": "2026-04-29",
      "value": 220.05
    },
    {
      "date": "2026-04-30",
      "value": 220.42
    },
    {
      "date": "2026-05-04",
      "value": 230.45
    },
    {
      "date": "2026-05-05",
      "value": 231.2
    },
    {
      "date": "2026-05-06",
      "value": 235.68
    },
    {
      "date": "2026-05-07",
      "value": 240.85
    },
    {
      "date": "2026-05-08",
      "value": 238.79
    },
    {
      "date": "2026-05-11",
      "value": 241.47
    },
    {
      "date": "2026-05-12",
      "value": 241.03
    },
    {
      "date": "2026-05-13",
      "value": 237.73
    },
    {
      "date": "2026-05-14",
      "value": 238.11
    },
    {
      "date": "2026-05-15",
      "value": 234.62
    },
    {
      "date": "2026-05-18",
      "value": 233.81
    },
    {
      "date": "2026-05-19",
      "value": 228.77
    },
    {
      "date": "2026-05-20",
      "value": 227.4
    },
    {
      "date": "2026-05-21",
      "value": 237.11
    },
    {
      "date": "2026-05-22",
      "value": 242.03
    },
    {
      "date": "2026-05-25",
      "value": 252.37
    },
    {
      "date": "2026-05-26",
      "value": 252.8
    },
    {
      "date": "2026-05-27",
      "value": 260.65
    },
    {
      "date": "2026-05-28",
      "value": 253.86
    },
    {
      "date": "2026-05-29",
      "value": 261.77
    },
    {
      "date": "2026-06-01",
      "value": 265.82
    },
    {
      "date": "2026-06-02",
      "value": 265.88
    },
    {
      "date": "2026-06-03",
      "value": 270.73
    },
    {
      "date": "2026-06-04",
      "value": 266.06
    },
    {
      "date": "2026-06-05",
      "value": 261.58
    },
    {
      "date": "2026-06-08",
      "value": 252.37
    },
    {
      "date": "2026-06-09",
      "value": 261.02
    },
    {
      "date": "2026-06-10",
      "value": 251.12
    },
    {
      "date": "2026-06-11",
      "value": 250.5
    },
    {
      "date": "2026-06-12",
      "value": 255.6
    },
    {
      "date": "2026-06-15",
      "value": 263.95
    },
    {
      "date": "2026-06-16",
      "value": 265.63
    },
    {
      "date": "2026-06-17",
      "value": 265.69
    },
    {
      "date": "2026-06-18",
      "value": 268.87
    },
    {
      "date": "2026-06-22",
      "value": 277.9
    },
    {
      "date": "2026-06-23",
      "value": 274.91
    },
    {
      "date": "2026-06-24",
      "value": 267.81
    },
    {
      "date": "2026-06-25",
      "value": 268.62
    },
    {
      "date": "2026-06-26",
      "value": 256.41
    },
    {
      "date": "2026-06-29",
      "value": 260.21
    },
    {
      "date": "2026-06-30",
      "value": 268.12
    },
    {
      "date": "2026-07-01",
      "value": 272.04
    },
    {
      "date": "2026-07-02",
      "value": 270.92
    },
    {
      "date": "2026-07-03",
      "value": 269.99
    },
    {
      "date": "2026-07-06",
      "value": 268.87
    },
    {
      "date": "2026-07-07",
      "value": 262.14
    },
    {
      "date": "2026-07-08",
      "value": 261.77
    },
    {
      "date": "2026-07-09",
      "value": 261.64
    },
    {
      "date": "2026-07-13",
      "value": 260.59
    },
    {
      "date": "2026-07-14",
      "value": 255.54
    },
    {
      "date": "2026-07-15",
      "value": 260.77
    },
    {
      "date": "2026-07-16",
      "value": 260.34
    },
    {
      "date": "2026-07-17",
      "value": 243.28
    },
    {
      "date": "2026-07-20",
      "value": 240.91
    },
    {
      "date": "2026-07-21",
      "value": 251.99
    },
    {
      "date": "2026-07-22",
      "value": 255.79
    }
  ],
  "top_holdings": [
    {
      "etf_id": "TW-00923",
      "holding_symbol": "2330.TW",
      "holding_name": "Taiwan Semiconductor Manufacturing Co Ltd",
      "weight": 0.43937778,
      "as_of": "2026-07-19",
      "source": "yahoo"
    },
    {
      "etf_id": "TW-00923",
      "holding_symbol": "2308.TW",
      "holding_name": "Delta Electronics Inc",
      "weight": 0.0658391,
      "as_of": "2026-07-19",
      "source": "yahoo"
    },
    {
      "etf_id": "TW-00923",
      "holding_symbol": "2317.TW",
      "holding_name": "Hon Hai Precision Industry Co Ltd",
      "weight": 0.052697703,
      "as_of": "2026-07-19",
      "source": "yahoo"
    },
    {
      "etf_id": "TW-00923",
      "holding_symbol": "2454.TW",
      "holding_name": "MediaTek Inc",
      "weight": 0.0515066,
      "as_of": "2026-07-19",
      "source": "yahoo"
    },
    {
      "etf_id": "TW-00923",
      "holding_symbol": "3711.TW",
      "holding_name": "ASE Technology Holding Co Ltd",
      "weight": 0.0243317,
      "as_of": "2026-07-19",
      "source": "yahoo"
    },
    {
      "etf_id": "TW-00923",
      "holding_symbol": "2383.TW",
      "holding_name": "Elite Material Co Ltd",
      "weight": 0.0216427,
      "as_of": "2026-07-19",
      "source": "yahoo"
    },
    {
      "etf_id": "TW-00923",
      "holding_symbol": "2345.TW",
      "holding_name": "Accton Technology Corp",
      "weight": 0.0178649,
      "as_of": "2026-07-19",
      "source": "yahoo"
    },
    {
      "etf_id": "TW-00923",
      "holding_symbol": "2382.TW",
      "holding_name": "Quanta Computer Inc",
      "weight": 0.0177841,
      "as_of": "2026-07-19",
      "source": "yahoo"
    },
    {
      "etf_id": "TW-00923",
      "holding_symbol": "3017.TW",
      "holding_name": "Asia Vital Components Co Ltd",
      "weight": 0.0170251,
      "as_of": "2026-07-19",
      "source": "yahoo"
    },
    {
      "etf_id": "TW-00923",
      "holding_symbol": "2891.TW",
      "holding_name": "CTBC Financial Holding Co Ltd",
      "weight": 0.0149914,
      "as_of": "2026-07-19",
      "source": "yahoo"
    }
  ],
  "holdings_summary": {
    "holding_count": 10,
    "top_10_weight": 0.723061,
    "top_3_weight": 0.557915
  }
}
