{
  "etf_id": "US-AIQ",
  "ticker": "AIQ",
  "quote_symbol": "AIQ",
  "name": "Global X Artificial Intelligence & Technology ETF",
  "short_name": "AIQ",
  "listing_market": "US",
  "listing_exchange": "NYSE/NASDAQ",
  "currency": "USD",
  "benchmark_symbol": "SPY",
  "benchmark_name": "S&P 500 ETF",
  "issuer": "Global X Artificial Intelligence & Technology",
  "asset_class": "equity",
  "is_thematic": true,
  "active": true,
  "classifications": [
    {
      "dimension": "theme",
      "code": "artificial_intelligence"
    },
    {
      "dimension": "region",
      "code": "global_or_us"
    },
    {
      "dimension": "ai_layer",
      "code": "ai_core"
    },
    {
      "dimension": "ai_layer",
      "code": "ai_platform"
    },
    {
      "dimension": "ai_layer",
      "code": "cloud"
    },
    {
      "dimension": "ai_layer",
      "code": "software"
    }
  ],
  "metrics": {},
  "latest_price": null,
  "trend": [],
  "top_holdings": [],
  "holdings_summary": {
    "holding_count": 0,
    "top_10_weight": 0,
    "top_3_weight": 0
  }
}
